opsctl/__init__.py
opsctl/bambooClient.py
opsctl/main.py
opsctl/render.py
opsctl-0.2.2.dist-info/LICENSE
opsctl-0.2.2.dist-info/METADATA
opsctl-0.2.2.dist-info/WHEEL
opsctl-0.2.2.dist-info/entry_points.txt
opsctl-0.2.2.dist-info/top_level.txt
opsctl-0.2.2.dist-info/RECORD
