Metadata-Version: 2.1
Name: opsctl
Version: 0.2.2
Summary: OPS CTL Tool
Home-page: https://github.com/seoktaehyeon/opsctl
Author: Will
Author-email: v.stone@163.com
Maintainer: Will
Maintainer-email: v.stone@163.com
License: MIT
Platform: any
License-File: LICENSE
Requires-Dist: PyYAML
Requires-Dist: requests
Requires-Dist: jinja2
